fabulaws/__init__.py
fabulaws/api.py
fabulaws/decorators.py
fabulaws/ec2.py
fabulaws/library/__init__.py
fabulaws/library/wsgiautoscale/__init__.py
fabulaws/library/wsgiautoscale/api.py
fabulaws/library/wsgiautoscale/servers.py
fabulaws/library/wsgiautoscale/templates/gunicorn-entrypoint.sh
fabulaws/library/wsgiautoscale/templates/logstash-agent.conf
fabulaws/library/wsgiautoscale/templates/logstash.conf
fabulaws/library/wsgiautoscale/templates/newrelic-infra.yml_template
fabulaws/library/wsgiautoscale/templates/newrelic-plugin-agent.cfg
fabulaws/library/wsgiautoscale/templates/newrelic.ini
fabulaws/library/wsgiautoscale/templates/nginx.conf
fabulaws/library/wsgiautoscale/templates/pgbouncer-users.txt
fabulaws/library/wsgiautoscale/templates/pgbouncer.ini
fabulaws/library/wsgiautoscale/templates/rsyslog.conf
fabulaws/library/wsgiautoscale/templates/stunnel.conf
fabulaws/library/wsgiautoscale/templates/sudoers
fabulaws/library/wsgiautoscale/templates/supervisor.conf
fabulaws/library/wsgiautoscale/templates/web-rc.local
fabulaws/library/wsgiautoscale/templates/awslogs/aws.conf
fabulaws/library/wsgiautoscale/templates/awslogs/awslogs.conf
fabulaws/library/wsgiautoscale/templates/awslogs/awslogs.service
fabulaws/ubuntu/__init__.py
fabulaws/ubuntu/instances/__init__.py
fabulaws/ubuntu/instances/base.py
fabulaws/ubuntu/instances/lucid.py
fabulaws/ubuntu/packages/__init__.py
fabulaws/ubuntu/packages/base.py
fabulaws/ubuntu/packages/fail2ban.py
fabulaws/ubuntu/packages/memcached.py
fabulaws/ubuntu/packages/mongodb.py
fabulaws/ubuntu/packages/postgres.py
fabulaws/ubuntu/packages/python.py
fabulaws/ubuntu/packages/rabbitmq.py
fabulaws/ubuntu/packages/redis.py
fabulaws/ubuntu/packages/shorewall.py
fabulaws-1.0.16.dist-info/METADATA
fabulaws-1.0.16.dist-info/WHEEL
fabulaws-1.0.16.dist-info/top_level.txt
fabulaws-1.0.16.dist-info/RECORD
