Metadata-Version: 2.1
Name: fabulaws
Version: 1.0.16
Summary: Simple tool for interacting with AWS in Python
Home-page: http://github.com/caktus/fabulaws/
Author: Caktus Consulting Group
Author-email: solutions@caktusgroup.com
License: BSD
Classifier: Topic :: System :: Systems Administration
Classifier: Intended Audience :: Developers
Classifier: License :: OSI Approved :: BSD License
Classifier: Programming Language :: Python
Classifier: Topic :: Software Development :: Libraries :: Python Modules
Classifier: Development Status :: 4 - Beta
Classifier: Operating System :: OS Independent
Classifier: Programming Language :: Python
Classifier: Programming Language :: Python :: 3
Classifier: Programming Language :: Python :: 3.8
Requires-Dist: pyyaml (<5.5,>=3.10)
Requires-Dist: boto (<3,>=2.39)
Requires-Dist: fabric (<2.0)
Requires-Dist: paramiko (==2.11.0)
